{
	"info": {
		"name": "School Manager API",
		"description": "Colección completa de endpoints para probar la API del sistema de gestión escolar",
		"schema": "https://schema.getpostman.com/json/collection/v2.1.0/collection.json"
	},
	"variable": [
		{
			"key": "base_url",
			"value": "http://localhost:8080/api/v1",
			"type": "string"
		},
		{
			"key": "token",
			"value": "",
			"type": "string"
		}
	],
	"item": [
		{
			"name": "Auth",
			"item": [
				{
					"name": "Register (Crear Escuela + Director)",
					"event": [
						{
							"listen": "test",
							"script": {
								"exec": [
									"if (pm.response.code === 201) {",
									"    var jsonData = pm.response.json();",
									"    pm.collectionVariables.set(\"token\", jsonData.data.token);",
									"    console.log(\"Token guardado:\", jsonData.data.token);",
									"}"
								],
								"type": "text/javascript"
							}
						}
					],
					"request": {
						"method": "POST",
						"header": [
							{
								"key": "Content-Type",
								"value": "application/json"
							}
						],
						"body": {
							"mode": "raw",
							"raw": "{\n    \"nombre_escuela\": \"Colegio San Francisco\",\n    \"slug\": \"colegio-san-francisco\",\n    \"cct\": \"14DPR0001X\",\n    \"rfc\": \"CSF850101ABC\",\n    \"email_escuela\": \"contacto@colegiosf.edu.mx\",\n    \"nombre\": \"Juan Pérez\",\n    \"email\": \"juan.perez@colegiosf.edu.mx\",\n    \"password\": \"password123\",\n    \"password_confirmation\": \"password123\"\n}"
						},
						"url": {
							"raw": "{{base_url}}/auth/register",
							"host": [
								"{{base_url}}"
							],
							"path": [
								"auth",
								"register"
							]
						}
					},
					"response": []
				},
				{
					"name": "Login",
					"event": [
						{
							"listen": "test",
							"script": {
								"exec": [
									"if (pm.response.code === 200) {",
									"    var jsonData = pm.response.json();",
									"    pm.collectionVariables.set(\"token\", jsonData.data.token);",
									"    console.log(\"Token guardado:\", jsonData.data.token);",
									"}"
								],
								"type": "text/javascript"
							}
						}
					],
					"request": {
						"method": "POST",
						"header": [
							{
								"key": "Content-Type",
								"value": "application/json"
							}
						],
						"body": {
							"mode": "raw",
							"raw": "{\n    \"email\": \"juan.perez@colegiosf.edu.mx\",\n    \"password\": \"password123\"\n}"
						},
						"url": {
							"raw": "{{base_url}}/auth/login",
							"host": [
								"{{base_url}}"
							],
							"path": [
								"auth",
								"login"
							]
						}
					},
					"response": []
				},
				{
					"name": "Me (Usuario Autenticado)",
					"request": {
						"method": "GET",
						"header": [
							{
								"key": "Authorization",
								"value": "Bearer {{token}}"
							}
						],
						"url": {
							"raw": "{{base_url}}/auth/me",
							"host": [
								"{{base_url}}"
							],
							"path": [
								"auth",
								"me"
							]
						}
					},
					"response": []
				},
				{
					"name": "Logout",
					"request": {
						"method": "POST",
						"header": [
							{
								"key": "Authorization",
								"value": "Bearer {{token}}"
							}
						],
						"url": {
							"raw": "{{base_url}}/auth/logout",
							"host": [
								"{{base_url}}"
							],
							"path": [
								"auth",
								"logout"
							]
						}
					},
					"response": []
				}
			]
		},
		{
			"name": "Niveles",
			"item": [
				{
					"name": "Listar Niveles",
					"request": {
						"method": "GET",
						"header": [
							{
								"key": "Authorization",
								"value": "Bearer {{token}}"
							}
						],
						"url": {
							"raw": "{{base_url}}/niveles",
							"host": [
								"{{base_url}}"
							],
							"path": [
								"niveles"
							]
						}
					},
					"response": []
				},
				{
					"name": "Crear Nivel",
					"request": {
						"method": "POST",
						"header": [
							{
								"key": "Authorization",
								"value": "Bearer {{token}}"
							},
							{
								"key": "Content-Type",
								"value": "application/json"
							}
						],
						"body": {
							"mode": "raw",
							"raw": "{\n    \"nombre\": \"primaria\"\n}"
						},
						"url": {
							"raw": "{{base_url}}/niveles",
							"host": [
								"{{base_url}}"
							],
							"path": [
								"niveles"
							]
						}
					},
					"response": []
				},
				{
					"name": "Ver Nivel",
					"request": {
						"method": "GET",
						"header": [
							{
								"key": "Authorization",
								"value": "Bearer {{token}}"
							}
						],
						"url": {
							"raw": "{{base_url}}/niveles/1",
							"host": [
								"{{base_url}}"
							],
							"path": [
								"niveles",
								"1"
							]
						}
					},
					"response": []
				},
				{
					"name": "Actualizar Nivel",
					"request": {
						"method": "PUT",
						"header": [
							{
								"key": "Authorization",
								"value": "Bearer {{token}}"
							},
							{
								"key": "Content-Type",
								"value": "application/json"
							}
						],
						"body": {
							"mode": "raw",
							"raw": "{\n    \"activo\": false\n}"
						},
						"url": {
							"raw": "{{base_url}}/niveles/1",
							"host": [
								"{{base_url}}"
							],
							"path": [
								"niveles",
								"1"
							]
						}
					},
					"response": []
				},
				{
					"name": "Eliminar Nivel",
					"request": {
						"method": "DELETE",
						"header": [
							{
								"key": "Authorization",
								"value": "Bearer {{token}}"
							}
						],
						"url": {
							"raw": "{{base_url}}/niveles/1",
							"host": [
								"{{base_url}}"
							],
							"path": [
								"niveles",
								"1"
							]
						}
					},
					"response": []
				}
			]
		},
		{
			"name": "Grados",
			"item": [
				{
					"name": "Listar Grados",
					"request": {
						"method": "GET",
						"header": [
							{
								"key": "Authorization",
								"value": "Bearer {{token}}"
							}
						],
						"url": {
							"raw": "{{base_url}}/grados",
							"host": [
								"{{base_url}}"
							],
							"path": [
								"grados"
							]
						}
					},
					"response": []
				},
				{
					"name": "Listar Grados por Nivel",
					"request": {
						"method": "GET",
						"header": [
							{
								"key": "Authorization",
								"value": "Bearer {{token}}"
							}
						],
						"url": {
							"raw": "{{base_url}}/grados?nivel_id=1",
							"host": [
								"{{base_url}}"
							],
							"path": [
								"grados"
							],
							"query": [
								{
									"key": "nivel_id",
									"value": "1"
								}
							]
						}
					},
					"response": []
				},
				{
					"name": "Crear Grado",
					"request": {
						"method": "POST",
						"header": [
							{
								"key": "Authorization",
								"value": "Bearer {{token}}"
							},
							{
								"key": "Content-Type",
								"value": "application/json"
							}
						],
						"body": {
							"mode": "raw",
							"raw": "{\n    \"nivel_id\": 1,\n    \"nombre\": \"3° Primaria\",\n    \"orden\": 3\n}"
						},
						"url": {
							"raw": "{{base_url}}/grados",
							"host": [
								"{{base_url}}"
							],
							"path": [
								"grados"
							]
						}
					},
					"response": []
				},
				{
					"name": "Ver Grado",
					"request": {
						"method": "GET",
						"header": [
							{
								"key": "Authorization",
								"value": "Bearer {{token}}"
							}
						],
						"url": {
							"raw": "{{base_url}}/grados/1",
							"host": [
								"{{base_url}}"
							],
							"path": [
								"grados",
								"1"
							]
						}
					},
					"response": []
				},
				{
					"name": "Actualizar Grado",
					"request": {
						"method": "PUT",
						"header": [
							{
								"key": "Authorization",
								"value": "Bearer {{token}}"
							},
							{
								"key": "Content-Type",
								"value": "application/json"
							}
						],
						"body": {
							"mode": "raw",
							"raw": "{\n    \"nombre\": \"Tercero de Primaria\"\n}"
						},
						"url": {
							"raw": "{{base_url}}/grados/1",
							"host": [
								"{{base_url}}"
							],
							"path": [
								"grados",
								"1"
							]
						}
					},
					"response": []
				},
				{
					"name": "Eliminar Grado",
					"request": {
						"method": "DELETE",
						"header": [
							{
								"key": "Authorization",
								"value": "Bearer {{token}}"
							}
						],
						"url": {
							"raw": "{{base_url}}/grados/1",
							"host": [
								"{{base_url}}"
							],
							"path": [
								"grados",
								"1"
							]
						}
					},
					"response": []
				}
			]
		},
		{
			"name": "Grupos",
			"item": [
				{
					"name": "Listar Grupos",
					"request": {
						"method": "GET",
						"header": [
							{
								"key": "Authorization",
								"value": "Bearer {{token}}"
							}
						],
						"url": {
							"raw": "{{base_url}}/grupos",
							"host": [
								"{{base_url}}"
							],
							"path": [
								"grupos"
							]
						}
					},
					"response": []
				},
				{
					"name": "Listar Grupos por Grado",
					"request": {
						"method": "GET",
						"header": [
							{
								"key": "Authorization",
								"value": "Bearer {{token}}"
							}
						],
						"url": {
							"raw": "{{base_url}}/grupos?grado_id=1",
							"host": [
								"{{base_url}}"
							],
							"path": [
								"grupos"
							],
							"query": [
								{
									"key": "grado_id",
									"value": "1"
								}
							]
						}
					},
					"response": []
				},
				{
					"name": "Crear Grupo",
					"request": {
						"method": "POST",
						"header": [
							{
								"key": "Authorization",
								"value": "Bearer {{token}}"
							},
							{
								"key": "Content-Type",
								"value": "application/json"
							}
						],
						"body": {
							"mode": "raw",
							"raw": "{\n    \"grado_id\": 1,\n    \"nombre\": \"Grupo A\",\n    \"capacidad_maxima\": 30\n}"
						},
						"url": {
							"raw": "{{base_url}}/grupos",
							"host": [
								"{{base_url}}"
							],
							"path": [
								"grupos"
							]
						}
					},
					"response": []
				},
				{
					"name": "Ver Grupo",
					"request": {
						"method": "GET",
						"header": [
							{
								"key": "Authorization",
								"value": "Bearer {{token}}"
							}
						],
						"url": {
							"raw": "{{base_url}}/grupos/1",
							"host": [
								"{{base_url}}"
							],
							"path": [
								"grupos",
								"1"
							]
						}
					},
					"response": []
				},
				{
					"name": "Actualizar Grupo",
					"request": {
						"method": "PUT",
						"header": [
							{
								"key": "Authorization",
								"value": "Bearer {{token}}"
							},
							{
								"key": "Content-Type",
								"value": "application/json"
							}
						],
						"body": {
							"mode": "raw",
							"raw": "{\n    \"capacidad_maxima\": 35,\n    \"maestro_id\": 1\n}"
						},
						"url": {
							"raw": "{{base_url}}/grupos/1",
							"host": [
								"{{base_url}}"
							],
							"path": [
								"grupos",
								"1"
							]
						}
					},
					"response": []
				},
				{
					"name": "Eliminar Grupo",
					"request": {
						"method": "DELETE",
						"header": [
							{
								"key": "Authorization",
								"value": "Bearer {{token}}"
							}
						],
						"url": {
							"raw": "{{base_url}}/grupos/1",
							"host": [
								"{{base_url}}"
							],
							"path": [
								"grupos",
								"1"
							]
						}
					},
					"response": []
				}
			]
		},
		{
			"name": "Padres",
			"item": [
				{
					"name": "Listar Padres",
					"request": {
						"method": "GET",
						"header": [
							{
								"key": "Authorization",
								"value": "Bearer {{token}}"
							}
						],
						"url": {
							"raw": "{{base_url}}/padres",
							"host": [
								"{{base_url}}"
							],
							"path": [
								"padres"
							]
						}
					},
					"response": []
				},
				{
					"name": "Buscar Padres",
					"request": {
						"method": "GET",
						"header": [
							{
								"key": "Authorization",
								"value": "Bearer {{token}}"
							}
						],
						"url": {
							"raw": "{{base_url}}/padres?search=Juan",
							"host": [
								"{{base_url}}"
							],
							"path": [
								"padres"
							],
							"query": [
								{
									"key": "search",
									"value": "Juan"
								}
							]
						}
					},
					"response": []
				},
				{
					"name": "Crear Padre",
					"request": {
						"method": "POST",
						"header": [
							{
								"key": "Authorization",
								"value": "Bearer {{token}}"
							},
							{
								"key": "Content-Type",
								"value": "application/json"
							}
						],
						"body": {
							"mode": "raw",
							"raw": "{\n    \"nombre_completo\": \"María González López\",\n    \"email\": \"maria.gonzalez@email.com\",\n    \"telefono\": \"4491234567\",\n    \"rfc\": \"GOLM850615ABC\",\n    \"regimen_fiscal\": \"605\",\n    \"uso_cfdi\": \"G03\",\n    \"codigo_postal\": \"20000\"\n}"
						},
						"url": {
							"raw": "{{base_url}}/padres",
							"host": [
								"{{base_url}}"
							],
							"path": [
								"padres"
							]
						}
					},
					"response": []
				},
				{
					"name": "Ver Padre",
					"request": {
						"method": "GET",
						"header": [
							{
								"key": "Authorization",
								"value": "Bearer {{token}}"
							}
						],
						"url": {
							"raw": "{{base_url}}/padres/1",
							"host": [
								"{{base_url}}"
							],
							"path": [
								"padres",
								"1"
							]
						}
					},
					"response": []
				},
				{
					"name": "Actualizar Padre",
					"request": {
						"method": "PUT",
						"header": [
							{
								"key": "Authorization",
								"value": "Bearer {{token}}"
							},
							{
								"key": "Content-Type",
								"value": "application/json"
							}
						],
						"body": {
							"mode": "raw",
							"raw": "{\n    \"telefono\": \"4499876543\",\n    \"regimen_fiscal\": \"612\"\n}"
						},
						"url": {
							"raw": "{{base_url}}/padres/1",
							"host": [
								"{{base_url}}"
							],
							"path": [
								"padres",
								"1"
							]
						}
					},
					"response": []
				},
				{
					"name": "Eliminar Padre",
					"request": {
						"method": "DELETE",
						"header": [
							{
								"key": "Authorization",
								"value": "Bearer {{token}}"
							}
						],
						"url": {
							"raw": "{{base_url}}/padres/1",
							"host": [
								"{{base_url}}"
							],
							"path": [
								"padres",
								"1"
							]
						}
					},
					"response": []
				}
			]
		},
		{
			"name": "Alumnos",
			"item": [
				{
					"name": "Listar Alumnos",
					"request": {
						"method": "GET",
						"header": [
							{
								"key": "Authorization",
								"value": "Bearer {{token}}"
							}
						],
						"url": {
							"raw": "{{base_url}}/alumnos",
							"host": [
								"{{base_url}}"
							],
							"path": [
								"alumnos"
							]
						}
					},
					"response": []
				},
				{
					"name": "Listar Alumnos por Grupo",
					"request": {
						"method": "GET",
						"header": [
							{
								"key": "Authorization",
								"value": "Bearer {{token}}"
							}
						],
						"url": {
							"raw": "{{base_url}}/alumnos?grupo_id=1",
							"host": [
								"{{base_url}}"
							],
							"path": [
								"alumnos"
							],
							"query": [
								{
									"key": "grupo_id",
									"value": "1"
								}
							]
						}
					},
					"response": []
				},
				{
					"name": "Crear Alumno con Padres",
					"request": {
						"method": "POST",
						"header": [
							{
								"key": "Authorization",
								"value": "Bearer {{token}}"
							},
							{
								"key": "Content-Type",
								"value": "application/json"
							}
						],
						"body": {
							"mode": "raw",
							"raw": "{\n    \"nombre\": \"Carlos\",\n    \"apellido_paterno\": \"Ramírez\",\n    \"apellido_materno\": \"Sánchez\",\n    \"curp\": \"RASC150823HDFMRL09\",\n    \"fecha_nacimiento\": \"2015-08-23\",\n    \"grupo_id\": 1,\n    \"padres\": [\n        {\n            \"padre_id\": 1,\n            \"parentesco\": \"madre\",\n            \"responsable_pagos\": true,\n            \"contacto_emergencia\": true\n        }\n    ]\n}"
						},
						"url": {
							"raw": "{{base_url}}/alumnos",
							"host": [
								"{{base_url}}"
							],
							"path": [
								"alumnos"
							]
						}
					},
					"response": []
				},
				{
					"name": "Ver Alumno",
					"request": {
						"method": "GET",
						"header": [
							{
								"key": "Authorization",
								"value": "Bearer {{token}}"
							}
						],
						"url": {
							"raw": "{{base_url}}/alumnos/1",
							"host": [
								"{{base_url}}"
							],
							"path": [
								"alumnos",
								"1"
							]
						}
					},
					"response": []
				},
				{
					"name": "Actualizar Alumno",
					"request": {
						"method": "PUT",
						"header": [
							{
								"key": "Authorization",
								"value": "Bearer {{token}}"
							},
							{
								"key": "Content-Type",
								"value": "application/json"
							}
						],
						"body": {
							"mode": "raw",
							"raw": "{\n    \"grupo_id\": 2,\n    \"activo\": true\n}"
						},
						"url": {
							"raw": "{{base_url}}/alumnos/1",
							"host": [
								"{{base_url}}"
							],
							"path": [
								"alumnos",
								"1"
							]
						}
					},
					"response": []
				},
				{
					"name": "Eliminar Alumno",
					"request": {
						"method": "DELETE",
						"header": [
							{
								"key": "Authorization",
								"value": "Bearer {{token}}"
							}
						],
						"url": {
							"raw": "{{base_url}}/alumnos/1",
							"host": [
								"{{base_url}}"
							],
							"path": [
								"alumnos",
								"1"
							]
						}
					},
					"response": []
				}
			]
		},
		{
			"name": "Test",
			"request": {
				"method": "GET",
				"header": [],
				"url": {
					"raw": "{{base_url}}/test",
					"host": [
						"{{base_url}}"
					],
					"path": [
						"test"
					]
				}
			},
			"response": []
		}
	]
}
